mlplatform_lib/__init__.py
mlplatform_lib/api_client.py
mlplatform_lib/auth.py
mlplatform_lib/automl/__init__.py
mlplatform_lib/automl/automl_api.py
mlplatform_lib/automl/automl_http_client.py
mlplatform_lib/dataclass/__init__.py
mlplatform_lib/dataclass/column_of_table_from_default_source.py
mlplatform_lib/dataclass/column_option.py
mlplatform_lib/dataclass/data_object.py
mlplatform_lib/dataclass/data_object_info_list.py
mlplatform_lib/dataclass/data_object_out_col.py
mlplatform_lib/dataclass/db_source_data_object_candidate.py
mlplatform_lib/dataclass/db_source_data_object_candidate_list.py
mlplatform_lib/dataclass/file_download.py
mlplatform_lib/dataclass/insert_tuple_object.py
mlplatform_lib/dataclass/row_option.py
mlplatform_lib/dataclass/selector_property.py
mlplatform_lib/dataclass/table_column_info.py
mlplatform_lib/dataclass/table_desc_info.py
mlplatform_lib/dataclass/table_from_default_datasource_info.py
mlplatform_lib/dataclass/experiment/__init__.py
mlplatform_lib/dataclass/experiment/experiment_automl_dto.py
mlplatform_lib/dataclass/experiment/experiment_data_object_info.py
mlplatform_lib/dataclass/experiment/experiment_mllab_dto.py
mlplatform_lib/dataclass/experiment/experiment_predefinedai_dto.py
mlplatform_lib/dataclass/experiment/type/__init__.py
mlplatform_lib/dataclass/experiment/type/experiment_type.py
mlplatform_lib/dataclass/inference/__init__.py
mlplatform_lib/dataclass/inference/inference_automl_dto.py
mlplatform_lib/dataclass/inference/inference_dto.py
mlplatform_lib/dataclass/inference/inference_predefinedai_dto.py
mlplatform_lib/dataclass/model/__init__.py
mlplatform_lib/dataclass/model/model_automl_best_dto.py
mlplatform_lib/dataclass/model/model_automl_dto.py
mlplatform_lib/dataclass/model/model_dto.py
mlplatform_lib/dataclass/model/model_info_dto.py
mlplatform_lib/dataclass/model/model_predefinedai_dto.py
mlplatform_lib/dataclass/model/type/__init__.py
mlplatform_lib-8.4.1.2.7.1.1.dist-info/DESCRIPTION.rst
mlplatform_lib-8.4.1.2.7.1.1.dist-info/METADATA
mlplatform_lib-8.4.1.2.7.1.1.dist-info/RECORD
mlplatform_lib-8.4.1.2.7.1.1.dist-info/WHEEL
mlplatform_lib-8.4.1.2.7.1.1.dist-info/metadata.json
mlplatform_lib-8.4.1.2.7.1.1.dist-info/top_level.txt
