Metadata-Version: 2.0
Name: mlplatform-lib
Version: 8.4.1.2.7.1.1
Summary: mlplatform_lib
Home-page: UNKNOWN
Author: mlplatform_lib
Author-email: mansu_kim@tmax.co.kr
License: UNKNOWN
Keywords: mlplatform_lib
Platform: UNKNOWN
Classifier: Programming Language :: Python :: 3.6
Requires-Python: >=3.6
Requires-Dist: pandas (>=1.0.1)
Requires-Dist: requests (>=2.25.1)
Requires-Dist: dataclasses-json (>=0.5.4)
Requires-Dist: inflection (>=0.5.1)
Requires-Dist: dataclasses (>=0.6)
